[
    {
        "a": 255,
        "b": 0,
        "g": 0,
        "r": 0
    },
    {
        "a": 255,
        "b": 18,
        "g": 19,
        "r": 25
    },
    {
        "a": 255,
        "b": 29,
        "g": 37,
        "r": 58
    },
    {
        "a": 255,
        "b": 33,
        "g": 59,
        "r": 98
    },
    {
        "a": 255,
        "b": 29,
        "g": 91,
        "r": 146
    },
    {
        "a": 255,
        "b": 19,
        "g": 138,
        "r": 201
    },
    {
        "a": 255,
        "b": 10,
        "g": 202,
        "r": 253
    }
]